factotum/__init__.py
factotum/diceware.py
factotum/diceware.wordlist.asc
factotum/factoriopath.py
factotum/factotum.py
factotum/newmap.py
factotum/rcon.py
factotum/settings.py
factotum/update.py
factotum-0.1.6.dist-info/DESCRIPTION.rst
factotum-0.1.6.dist-info/METADATA
factotum-0.1.6.dist-info/RECORD
factotum-0.1.6.dist-info/WHEEL
factotum-0.1.6.dist-info/entry_points.txt
factotum-0.1.6.dist-info/metadata.json
factotum-0.1.6.dist-info/top_level.txt
