Metadata-Version: 2.0
Name: factotum
Version: 0.1.6
Summary: A tool to control a headless factorio server.
Home-page: https://github.com/Denubis/factotum
Author: Brian Ballsun-Stanton
Author-email: factorio@drbbs.org
License: GPLv3
Keywords: factorio rcon headless
Platform: UNKNOWN
Classifier: Development Status :: 4 - Beta
Classifier: Topic :: Games/Entertainment :: Simulation
Classifier: License :: OSI Approved :: GNU General Public License v3 or later (GPLv3+)
Requires-Dist: circus
Requires-Dist: click (>=5,<6)
Requires-Dist: clint
Requires-Dist: daemonocle
Requires-Dist: factoirc
Requires-Dist: ptyprocess
Requires-Dist: pyfakefs
Requires-Dist: python-valve
Requires-Dist: requests
